docparser_remittance_processor.py
docparser_remittance_processor-7.0.dist-info/METADATA
docparser_remittance_processor-7.0.dist-info/WHEEL
docparser_remittance_processor-7.0.dist-info/top_level.txt
docparser_remittance_processor-7.0.dist-info/RECORD
