Metadata-Version: 2.1
Name: docparser-remittance-processor
Version: 7.0
Summary: UNKNOWN
Home-page: UNKNOWN
Author: Hudge
Author-email: 
License: UNKNOWN
Platform: UNKNOWN
Classifier: Programming Language :: Python :: 3
Classifier: License :: OSI Approved :: MIT License
Classifier: Operating System :: OS Independent
Requires-Dist: xlrd
Requires-Dist: money2float
Requires-Dist: semi-structured-text-extractor
Requires-Dist: split-alphanumeric
